wrap_mENdRU/__init__.py
wrap_mENdRU/actions.py
wrap_mENdRU/const.py
wrap_mENdRU/event_decorators.py
wrap_mENdRU/sprite.py
wrap_mENdRU/sprite_text.py
wrap_mENdRU/world.py
wrap_mENdRU-0.1.1.1.dist-info/METADATA
wrap_mENdRU-0.1.1.1.dist-info/WHEEL
wrap_mENdRU-0.1.1.1.dist-info/top_level.txt
wrap_mENdRU-0.1.1.1.dist-info/RECORD
