Metadata-Version: 2.1
Name: wrap-mENdRU
Version: 0.1.1.1
Summary: UNKNOWN
Home-page: UNKNOWN
Author: UNKNOWN
Author-email: UNKNOWN
License: UNKNOWN
Platform: UNKNOWN
Requires-Dist: wrap-py (==0.2.*,>=0.2.2.1)
